claspy/__init__.py
claspy/clasp.py
claspy/data_loader.py
claspy/distance.py
claspy/nearest_neighbour.py
claspy/scoring.py
claspy/segmentation.py
claspy/utils.py
claspy/validation.py
claspy/window_size.py
claspy/streaming/__init__.py
claspy/streaming/clasp.py
claspy/streaming/nearest_neighbour.py
claspy/streaming/segmentation.py
claspy/tests/__init__.py
claspy/tests/clasp_test.py
claspy/tests/data_loader_test.py
claspy/tests/evaluation.py
claspy/tests/nearest_neighbour_test.py
claspy/tests/segmentation_test.py
claspy/tests/streaming_clasp_test.py
claspy/tests/streaming_nearest_neighbour_test.py
claspy/tests/streaming_segmentation_test.py
claspy/tests/window_size_test.py
claspy-0.2.7.dist-info/licenses/LICENSE
claspy-0.2.7.dist-info/METADATA
claspy-0.2.7.dist-info/WHEEL
claspy-0.2.7.dist-info/top_level.txt
claspy-0.2.7.dist-info/RECORD
