Metadata-Version: 2.4
Name: claspy
Version: 0.2.7
Home-page: https://github.com/ermshaua/claspy
Author: Arik Ermshaus
Author-email: Arik Ermshaus <ermshaua@informatik.hu-berlin.de>
License: BSD 3-Clause License
Project-URL: repository, https://github.com/ermshaua/claspy
Keywords: machine-learning,time-series,unsupervised-learning,segmentation,change-points
Classifier: Intended Audience :: Science/Research
Classifier: Intended Audience :: Developers
Classifier: License :: OSI Approved :: BSD License
Classifier: Programming Language :: Python
Classifier: Topic :: Software Development
Classifier: Topic :: Scientific/Engineering
Classifier: Operating System :: Microsoft :: Windows
Classifier: Operating System :: POSIX
Classifier: Operating System :: Unix
Classifier: Operating System :: MacOS
Classifier: Programming Language :: Python :: 3.7
Classifier: Programming Language :: Python :: 3.8
Classifier: Programming Language :: Python :: 3.9
Classifier: Programming Language :: Python :: 3.10
Classifier: Programming Language :: Python :: 3.11
Classifier: Programming Language :: Python :: 3.12
Requires-Python: >=3.7,<3.13
License-File: LICENSE
Requires-Dist: numpy<2.3.0,>=1.21.0
Requires-Dist: numba<0.62.0,>=0.55
Requires-Dist: pandas<2.4.0,>=2.0.0
Requires-Dist: scikit-learn<1.8.0,>=1.0.0
Requires-Dist: scipy<1.16.0,>=1.9.0
Requires-Dist: statsmodels>=0.12.1
Requires-Dist: matplotlib>=3.3.2
Requires-Dist: daproli>=0.22
Dynamic: author
Dynamic: home-page
Dynamic: license-file
Dynamic: requires-python
